dhlibs/__init__.py
dhlibs/_typing.py
dhlibs/alias_callable.py
dhlibs/cachedop/__init__.py
dhlibs/cachedop/_typings.py
dhlibs/cachedop/_utils.py
dhlibs/cachedop/audit.py
dhlibs/cachedop/audit.pyi
dhlibs/cachedop/core.py
dhlibs/cachedop/core.pyi
dhlibs/indices.py
dhlibs/options.py
dhlibs/py.typed
dhlibs/randfunc.py
dhlibs/reprfmt/__init__.py
dhlibs/reprfmt/constants.py
dhlibs/reprfmt/core.py
dhlibs/reprfmt/deco.py
dhlibs/reprfmt/dispatchers.py
dhlibs/reprfmt/formatters/__init__.py
dhlibs/reprfmt/formatters/base.py
dhlibs/reprfmt/formatters/default.py
dhlibs/reprfmt/formatters/others.py
dhlibs/reprfmt/formatters/useful.py
dhlibs/reprfmt/options.py
dhlibs/reprfmt/utils.py
dhlibs-0.1.8.dist-info/LICENSE
dhlibs-0.1.8.dist-info/LICENSE.APACHE
dhlibs-0.1.8.dist-info/LICENSE.MIT
dhlibs-0.1.8.dist-info/LICENSE.MPL
dhlibs-0.1.8.dist-info/METADATA
dhlibs-0.1.8.dist-info/WHEEL
dhlibs-0.1.8.dist-info/RECORD
